do_while/__init__.py
do_while/__version__.py
do_while/py.typed
do_while/tests.py
do_while-4.2.7.dist-info/licenses/LICENSE
do_while-4.2.7.dist-info/WHEEL
do_while-4.2.7.dist-info/METADATA
do_while-4.2.7.dist-info/RECORD
