Metadata-Version: 2.4
Name: do-while
Version: 4.2.7
Summary: making poor life choices for conference talks
Author-email: Amethyst Reese <amethyst@n7.gg>
Requires-Python: >=3.10
License-Expression: MIT
License-File: LICENSE
Requires-Dist: attribution>=1.8 ; extra == "dev"
Requires-Dist: black==24.8.0 ; extra == "dev"
Requires-Dist: build>=1.2 ; extra == "dev"
Requires-Dist: flake8==7.1.1 ; extra == "dev"
Requires-Dist: mypy==1.11.2 ; extra == "dev"
Requires-Dist: ufmt==2.7.2 ; extra == "dev"
Requires-Dist: usort==1.0.8 ; extra == "dev"
Project-URL: Home, https://github.com/amyreese/python-do-while
Provides-Extra: dev
